SOMcreator/__init__.py
SOMcreator/classes.py
SOMcreator/Template/__init__.py
SOMcreator/Template/bookmark_template.txt
SOMcreator/Template/fast_template.txt
SOMcreator/Template/ifc.json
SOMcreator/Template/mapping_template.txt
SOMcreator/Template/template.txt
SOMcreator/Template/untested_template.txt
SOMcreator/Template/__pyinstaller/__init__.py
SOMcreator/Template/__pyinstaller/hook-SOMcreator.py
SOMcreator/Template/js_templates/start_check_start.js
SOMcreator/Template/js_templates/start_koordinaten.js
SOMcreator/bsdd/__init__.py
SOMcreator/bsdd/transformer.py
SOMcreator/bsdd/tables/_attribute_helper.py
SOMcreator/constants/__init__.py
SOMcreator/constants/ifc_datatypes.py
SOMcreator/constants/json_constants.py
SOMcreator/constants/log_constants.py
SOMcreator/constants/value_constants.py
SOMcreator/core/__init__.py
SOMcreator/core/export_excel.py
SOMcreator/core/ifctosql.py
SOMcreator/external_software/__init__.py
SOMcreator/external_software/allplan.py
SOMcreator/external_software/card1.py
SOMcreator/external_software/revit.py
SOMcreator/external_software/vestra.py
SOMcreator/external_software/IDS/__init__.py
SOMcreator/external_software/IDS/ids_xsd.py
SOMcreator/external_software/IDS/main.py
SOMcreator/external_software/IDS/xml_xsd.py
SOMcreator/external_software/__pyinstaller/__init__.py
SOMcreator/external_software/__pyinstaller/hook-SOMcreator.py
SOMcreator/external_software/bim_collab_zoom/__init__.py
SOMcreator/external_software/bim_collab_zoom/action.py
SOMcreator/external_software/bim_collab_zoom/condition.py
SOMcreator/external_software/bim_collab_zoom/constants.py
SOMcreator/external_software/bim_collab_zoom/modelcheck.py
SOMcreator/external_software/bim_collab_zoom/rule.py
SOMcreator/external_software/desite/__init__.py
SOMcreator/external_software/desite/attribute_json.py
SOMcreator/external_software/desite/bill_of_quantities.py
SOMcreator/external_software/desite/bookmarks.py
SOMcreator/external_software/desite/building_structure.py
SOMcreator-1.7.7.dist-info/LICENSE
SOMcreator-1.7.7.dist-info/METADATA
SOMcreator-1.7.7.dist-info/WHEEL
SOMcreator-1.7.7.dist-info/entry_points.txt
SOMcreator-1.7.7.dist-info/top_level.txt
SOMcreator-1.7.7.dist-info/RECORD
