Metadata-Version: 2.1
Name: SOMcreator
Version: 1.7.7
Summary: create simple Datastructures for BIM Models
License: MIT License
Keywords: BIM,SOM
Classifier: Programming Language :: Python :: 3
Requires-Python: >=3.9
License-File: LICENSE
Requires-Dist: lxml
Requires-Dist: jinja2
Requires-Dist: openpyxl
Requires-Dist: anytree
